code_index.py
database_manager.py
embedding_helper.py
mcp_server.py
server.py
turboprop/__init__.py
turboprop/__main__.py
turboprop/_version.py
turboprop-0.2.2.dist-info/METADATA
turboprop-0.2.2.dist-info/WHEEL
turboprop-0.2.2.dist-info/entry_points.txt
turboprop-0.2.2.dist-info/top_level.txt
turboprop-0.2.2.dist-info/RECORD
