Metadata-Version: 2.4
Name: turboprop
Version: 0.2.2
Summary: Lightning-fast semantic code search and indexing with DuckDB vector operations
Author-email: Greg Lamp <greg@example.com>
License: MIT
Project-URL: Homepage, https://github.com/glamp/turboprop
Project-URL: Repository, https://github.com/glamp/turboprop
Project-URL: Issues, https://github.com/glamp/turboprop/issues
Keywords: code,search,semantic,embedding,mcp,ai,indexing
Classifier: Development Status :: 4 - Beta
Classifier: Intended Audience :: Developers
Classifier: License :: OSI Approved :: MIT License
Classifier: Programming Language :: Python :: 3
Classifier: Programming Language :: Python :: 3.12
Classifier: Programming Language :: Python :: 3.13
Classifier: Topic :: Software Development :: Libraries
Classifier: Topic :: Text Processing :: Indexing
Classifier: Topic :: Scientific/Engineering :: Artificial Intelligence
Requires-Python: >=3.11
Requires-Dist: duckdb>=1.3.2
Requires-Dist: fastapi>=0.116.1
Requires-Dist: uvicorn>=0.35.0
Requires-Dist: sentence-transformers>=5.0.0
Requires-Dist: transformers>=4.53.2
Requires-Dist: watchdog>=6.0.0
Requires-Dist: tqdm>=4.65.0
Requires-Dist: mcp>=1.0.0
Provides-Extra: dev
Requires-Dist: pytest>=7.0.0; extra == "dev"
Requires-Dist: pytest-cov>=4.0.0; extra == "dev"
